dgp_oauth2/VERSION
dgp_oauth2/__init__.py
dgp_oauth2/blueprint.py
dgp_oauth2/controllers.py
dgp_oauth2/credentials.py
dgp_oauth2/extensions.py
dgp_oauth2/lib.py
dgp_oauth2/logger.py
dgp_oauth2/models.py
dgp_oauth2/permissions.py
sample_extension/__init__.py
sample_permission_provider/__init__.py
dgp_oauth2-1.3.4.dist-info/LICENSE
dgp_oauth2-1.3.4.dist-info/METADATA
dgp_oauth2-1.3.4.dist-info/WHEEL
dgp_oauth2-1.3.4.dist-info/top_level.txt
dgp_oauth2-1.3.4.dist-info/RECORD
