Metadata-Version: 2.1
Name: dgp-oauth2
Version: 1.3.4
Summary: {{ DESCRIPTION }}
Home-page: https://github.com/dataspot/dgp-oauth2
Author: Adam Kariv, Open Knowledge (International), Datopian
License: MIT
Keywords: data,authentication,oauth2
Classifier: Development Status :: 4 - Beta
Classifier: Environment :: Web Environment
Classifier: Intended Audience :: Developers
Classifier: License :: OSI Approved :: MIT License
Classifier: Operating System :: OS Independent
Classifier: Programming Language :: Python :: 3.6
Classifier: Topic :: Internet :: WWW/HTTP :: Dynamic Content
Classifier: Topic :: Software Development :: Libraries :: Python Modules
License-File: LICENSE
Requires-Dist: flask
Requires-Dist: flask-cors
Requires-Dist: flask-jsonpify
Requires-Dist: authlib
Requires-Dist: pyjwt
Requires-Dist: sqlalchemy
Requires-Dist: cryptography
Requires-Dist: psycopg2-binary
Requires-Dist: requests
Provides-Extra: develop
Requires-Dist: pylama ; extra == 'develop'
Requires-Dist: tox ; extra == 'develop'
Requires-Dist: coverage ; extra == 'develop'
Requires-Dist: coveralls ; extra == 'develop'
Requires-Dist: pytest ; extra == 'develop'
Requires-Dist: pytest-cov ; extra == 'develop'
Requires-Dist: requests-mock (==1.3.0) ; extra == 'develop'
